{
  "metal": "aluminum",
  "analysis_date": "2025-08-07T16:04:21.200995",
  "search_methodology": {
    "method": "exact_sic",
    "confidence_level": "high",
    "search_criteria": {
      "exact_sic_codes": [
        "Alumina",
        "Aluminum Ore-Bauxite"
      ],
      "controlled_keywords": [],
      "sic_patterns": [],
      "operator_keywords": [
        "alcoa",
        "almatis",
        "alumina",
        "aluminum"
      ],
      "exclude_terms": []
    }
  },
  "summary_statistics": {
    "total_mines_identified": 53,
    "active_production_mines": 8,
    "inactive_or_non_producing_mines": 45,
    "total_estimated_production_mt_per_year": 1903000.0,
    "total_employment": 875,
    "expected_us_production_level": "significant"
  },
  "all_identified_mines": [
    {
      "mine_id": 100650,
      "mine_name": "Mobile Aluminum Refining Plant",
      "operator": "Aluminum Company Of America",
      "state": "AL",
      "county": "",
      "status": "Abandoned",
      "mine_type": "Facility",
      "primary_sic": "Alumina",
      "secondary_sic": NaN,
      "longitude": NaN,
      "latitude": NaN,
      "employees_reported": 0,
      "is_active_producer": false,
      "estimated_annual_production_mt": 0,
      "recent_production_records": [],
      "company_type": "Other",
      "primary_activity": "",
      "operating_since": "",
      "no_employees": NaN,
      "avg_employees_5yr": 0
    },
    {
      "mine_id": 103075,
      "mine_name": "EPCO PITS",
      "operator": "Eufaula Pulpwood Company Inc",
      "state": "AL",
      "county": "",
      "status": "Abandoned",
      "mine_type": "Surface",
      "primary_sic": "Aluminum Ore-Bauxite",
      "secondary_sic": NaN,
      "longitude": NaN,
      "latitude": NaN,
      "employees_reported": 2,
      "is_active_producer": false,
      "estimated_annual_production_mt": 0,
      "recent_production_records": [],
      "company_type": "Other",
      "primary_activity": "",
      "operating_since": "",
      "no_employees": 2.0,
      "avg_employees_5yr": 0
    },
    {
      "mine_id": 103424,
      "mine_name": "Universal Understanding",
      "operator": "Cumbie Inc.",
      "state": "AL",
      "county": "",
      "status": "Abandoned",
      "mine_type": "Surface",
      "primary_sic": "Aluminum Ore-Bauxite",
      "secondary_sic": NaN,
      "longitude": -85.145556,
      "latitude": 31.891389,
      "employees_reported": 0,
      "is_active_producer": false,
      "estimated_annual_production_mt": 0,
      "recent_production_records": [],
      "company_type": "Corporation",
      "primary_activity": "",
      "operating_since": "",
      "no_employees": 0.0,
      "avg_employees_5yr": 0
    },
    {
      "mine_id": 103509,
      "mine_name": "Vickers",
      "operator": "Cumbie Inc.",
      "state": "AL",
      "county": "",
      "status": "Abandoned",
      "mine_type": "Surface",
      "primary_sic": "Aluminum Ore-Bauxite",
      "secondary_sic": NaN,
      "longitude": -85.343889,
      "latitude": 31.748333,
      "employees_reported": 0,
      "is_active_producer": false,
      "estimated_annual_production_mt": 0,
      "recent_production_records": [],
      "company_type": "Corporation",
      "primary_activity": "",
      "operating_since": "",
      "no_employees": 0.0,
      "avg_employees_5yr": 0
    },
    {
      "mine_id": 300069,
      "mine_name": "Hurricane Creek",
      "operator": "Reynolds Metals Company",
      "state": "AR",
      "county": "",
      "status": "Abandoned",
      "mine_type": "Facility",
      "primary_sic": "Alumina",
      "secondary_sic": NaN,
      "longitude": NaN,
      "latitude": NaN,
      "employees_reported": 0,
      "is_active_producer": false,
      "estimated_annual_production_mt": 0,
      "recent_production_records": [],
      "company_type": "Other",
      "primary_activity": "",
      "operating_since": "",
      "no_employees": NaN,
      "avg_employees_5yr": 0
    },
    {
      "mine_id": 300145,
      "mine_name": "Bierman-Coe",
      "operator": "Porocel Corp",
      "state": "AR",
      "county": "",
      "status": "Abandoned",
      "mine_type": "Surface",
      "primary_sic": "Aluminum Ore-Bauxite",
      "secondary_sic": NaN,
      "longitude": NaN,
      "latitude": NaN,
      "employees_reported": 0,
      "is_active_producer": false,
      "estimated_annual_production_mt": 0,
      "recent_production_records": [],
      "company_type": "Corporation",
      "primary_activity": "",
      "operating_since": "",
      "no_employees": NaN,
      "avg_employees_5yr": 0
    },
    {
      "mine_id": 300257,
      "mine_name": "Arkansas Operations Mill",
      "operator": "Almatis Inc",
      "state": "AR",
      "county": "",
      "status": "Active",
      "mine_type": "Facility",
      "primary_sic": "Alumina",
      "secondary_sic": NaN,
      "longitude": -92.535278,
      "latitude": 34.582778,
      "employees_reported": 140,
      "is_active_producer": true,
      "estimated_annual_production_mt": 308000.0,
      "recent_production_records": [],
      "company_type": "Corporation",
      "primary_activity": "",
      "operating_since": "",
      "no_employees": 140.0,
      "avg_employees_5yr": 0
    },
    {
      "mine_id": 300261,
      "mine_name": "U.S. Vanadium - Benton, LLC",
      "operator": "US Vanadium - Benton, LLC",
      "state": "AR",
      "county": "",
      "status": "Active",
      "mine_type": "Surface",
      "primary_sic": "Aluminum Ore-Bauxite",
      "secondary_sic": NaN,
      "longitude": -92.516389,
      "latitude": 34.583889,
      "employees_reported": 5,
      "is_active_producer": true,
      "estimated_annual_production_mt": 11000.0,
      "recent_production_records": [],
      "company_type": "Other",
      "primary_activity": "",
      "operating_since": "",
      "no_employees": 5.0,
      "avg_employees_5yr": 0
    },
    {
      "mine_id": 300262,
      "mine_name": "Saline County Mines",
      "operator": "Reynolds Metals Company",
      "state": "AR",
      "county": "",
      "status": "Abandoned",
      "mine_type": "Surface",
      "primary_sic": "Aluminum Ore-Bauxite",
      "secondary_sic": NaN,
      "longitude": NaN,
      "latitude": NaN,
      "employees_reported": 0,
      "is_active_producer": false,
      "estimated_annual_production_mt": 0,
      "recent_production_records": [],
      "company_type": "Other",
      "primary_activity": "",
      "operating_since": "",
      "no_employees": NaN,
      "avg_employees_5yr": 0
    },
    {
      "mine_id": 300470,
      "mine_name": "Berger Plant",
      "operator": "Porocel Corp",
      "state": "AR",
      "county": "",
      "status": "Abandoned",
      "mine_type": "Facility",
      "primary_sic": "Aluminum Ore-Bauxite",
      "secondary_sic": NaN,
      "longitude": -92.336383,
      "latitude": 34.566099,
      "employees_reported": 0,
      "is_active_producer": false,
      "estimated_annual_production_mt": 0,
      "recent_production_records": [],
      "company_type": "Corporation",
      "primary_activity": "",
      "operating_since": "",
      "no_employees": 0.0,
      "avg_employees_5yr": 0
    },
    {
      "mine_id": 300472,
      "mine_name": "Arkansas Operations Mine",
      "operator": "Alcoa Inc",
      "state": "AR",
      "county": "",
      "status": "Abandoned",
      "mine_type": "Surface",
      "primary_sic": "Aluminum Ore-Bauxite",
      "secondary_sic": NaN,
      "longitude": -92.504482,
      "latitude": 34.548488,
      "employees_reported": 0,
      "is_active_producer": false,
      "estimated_annual_production_mt": 0,
      "recent_production_records": [],
      "company_type": "Corporation",
      "primary_activity": "",
      "operating_since": "",
      "no_employees": 0.0,
      "avg_employees_5yr": 0
    },
    {
      "mine_id": 300481,
      "mine_name": "ARKANSAS CALCINE MILL",
      "operator": "Harbison-Walker Refractories Company",
      "state": "AR",
      "county": "",
      "status": "Abandoned",
      "mine_type": "Facility",
      "primary_sic": "Aluminum Ore-Bauxite",
      "secondary_sic": NaN,
      "longitude": NaN,
      "latitude": NaN,
      "employees_reported": 0,
      "is_active_producer": false,
      "estimated_annual_production_mt": 0,
      "recent_production_records": [],
      "company_type": "Other",
      "primary_activity": "",
      "operating_since": "",
      "no_employees": 0.0,
      "avg_employees_5yr": 0
    },
    {
      "mine_id": 300537,
      "mine_name": "Little Rock Plant",
      "operator": "G2O Technologies",
      "state": "AR",
      "county": "",
      "status": "Abandoned",
      "mine_type": "Facility",
      "primary_sic": "Aluminum Ore-Bauxite",
      "secondary_sic": NaN,
      "longitude": -92.306111,
      "latitude": 34.656389,
      "employees_reported": 0,
      "is_active_producer": false,
      "estimated_annual_production_mt": 0,
      "recent_production_records": [],
      "company_type": "Corporation",
      "primary_activity": "",
      "operating_since": "",
      "no_employees": NaN,
      "avg_employees_5yr": 0
    },
    {
      "mine_id": 301141,
      "mine_name": "Pulaski County Pits",
      "operator": "Reynolds Metals Company",
      "state": "AR",
      "county": "",
      "status": "Abandoned",
      "mine_type": "Surface",
      "primary_sic": "Aluminum Ore-Bauxite",
      "secondary_sic": NaN,
      "longitude": NaN,
      "latitude": NaN,
      "employees_reported": 0,
      "is_active_producer": false,
      "estimated_annual_production_mt": 0,
      "recent_production_records": [],
      "company_type": "Other",
      "primary_activity": "",
      "operating_since": "",
      "no_employees": NaN,
      "avg_employees_5yr": 0
    },
    {
      "mine_id": 301178,
      "mine_name": "Alumina Pilot Plant",
      "operator": "Reynolds Metals Company",
      "state": "AR",
      "county": "",
      "status": "Abandoned",
      "mine_type": "Facility",
      "primary_sic": "Alumina",
      "secondary_sic": NaN,
      "longitude": NaN,
      "latitude": NaN,
      "employees_reported": 0,
      "is_active_producer": false,
      "estimated_annual_production_mt": 0,
      "recent_production_records": [],
      "company_type": "Other",
      "primary_activity": "",
      "operating_since": "",
      "no_employees": NaN,
      "avg_employees_5yr": 0
    },
    {
      "mine_id": 301361,
      "mine_name": "Elkins Pit",
      "operator": "Mc George Contracting Company Inc",
      "state": "AR",
      "county": "",
      "status": "Abandoned",
      "mine_type": "Surface",
      "primary_sic": "Aluminum Ore-Bauxite",
      "secondary_sic": NaN,
      "longitude": NaN,
      "latitude": NaN,
      "employees_reported": 0,
      "is_active_producer": false,
      "estimated_annual_production_mt": 0,
      "recent_production_records": [],
      "company_type": "Other",
      "primary_activity": "",
      "operating_since": "",
      "no_employees": NaN,
      "avg_employees_5yr": 0
    },
    {
      "mine_id": 301759,
      "mine_name": "SHOP EAST PIT",
      "operator": "Mc George Contracting Company Inc",
      "state": "AR",
      "county": "",
      "status": "Abandoned",
      "mine_type": "Surface",
      "primary_sic": "Aluminum Ore-Bauxite",
      "secondary_sic": NaN,
      "longitude": NaN,
      "latitude": NaN,
      "employees_reported": 0,
      "is_active_producer": false,
      "estimated_annual_production_mt": 0,
      "recent_production_records": [],
      "company_type": "Other",
      "primary_activity": "",
      "operating_since": "",
      "no_employees": 0.0,
      "avg_employees_5yr": 0
    },
    {
      "mine_id": 301926,
      "mine_name": "Alabama Mine",
      "operator": "McGeorge Contracting Co., Inc.",
      "state": "AR",
      "county": "",
      "status": "Intermittent",
      "mine_type": "Surface",
      "primary_sic": "Aluminum Ore-Bauxite",
      "secondary_sic": NaN,
      "longitude": -92.506667,
      "latitude": 34.558611,
      "employees_reported": 6,
      "is_active_producer": false,
      "estimated_annual_production_mt": 0,
      "recent_production_records": [],
      "company_type": "Corporation",
      "primary_activity": "",
      "operating_since": "",
      "no_employees": 6.0,
      "avg_employees_5yr": 0
    },
    {
      "mine_id": 301977,
      "mine_name": "Section 13",
      "operator": "Grant Garrett Excavating Inc",
      "state": "AR",
      "county": "",
      "status": "Abandoned",
      "mine_type": "Surface",
      "primary_sic": "Aluminum Ore-Bauxite",
      "secondary_sic": NaN,
      "longitude": NaN,
      "latitude": NaN,
      "employees_reported": 0,
      "is_active_producer": false,
      "estimated_annual_production_mt": 0,
      "recent_production_records": [],
      "company_type": "Corporation",
      "primary_activity": "",
      "operating_since": "",
      "no_employees": 0.0,
      "avg_employees_5yr": 0
    },
    {
      "mine_id": 301979,
      "mine_name": "Section 27",
      "operator": "SEMCOA",
      "state": "AR",
      "county": "",
      "status": "Active",
      "mine_type": "Surface",
      "primary_sic": "Aluminum Ore-Bauxite",
      "secondary_sic": NaN,
      "longitude": -92.513611,
      "latitude": 34.535,
      "employees_reported": 27,
      "is_active_producer": true,
      "estimated_annual_production_mt": 59400.0,
      "recent_production_records": [],
      "company_type": "Partnership",
      "primary_activity": "",
      "operating_since": "",
      "no_employees": 27.0,
      "avg_employees_5yr": 0
    },
    {
      "mine_id": 302023,
      "mine_name": "Huber Specialty Hydrates, LLC ",
      "operator": "Huber Specialty Hydrates, LLC ",
      "state": "AR",
      "county": "",
      "status": "Active",
      "mine_type": "Facility",
      "primary_sic": "Aluminum Ore-Bauxite",
      "secondary_sic": NaN,
      "longitude": -92.535278,
      "latitude": 34.582778,
      "employees_reported": 80,
      "is_active_producer": true,
      "estimated_annual_production_mt": 176000.0,
      "recent_production_records": [],
      "company_type": "Other",
      "primary_activity": "",
      "operating_since": "",
      "no_employees": 80.0,
      "avg_employees_5yr": 0
    },
    {
      "mine_id": 302033,
      "mine_name": "Section 20 Mines",
      "operator": "McGeorge Contracting Co., Inc.",
      "state": "AR",
      "county": "",
      "status": "Abandoned",
      "mine_type": "Surface",
      "primary_sic": "Aluminum Ore-Bauxite",
      "secondary_sic": NaN,
      "longitude": -92.508611,
      "latitude": 34.5575,
      "employees_reported": 0,
      "is_active_producer": false,
      "estimated_annual_production_mt": 0,
      "recent_production_records": [],
      "company_type": "Corporation",
      "primary_activity": "",
      "operating_since": "",
      "no_employees": 0.0,
      "avg_employees_5yr": 0
    },
    {
      "mine_id": 900684,
      "mine_name": "Andersonville Plant",
      "operator": "FBX Ceramics Holdings nka US Ceramics, LLC",
      "state": "GA",
      "county": "",
      "status": "Abandoned",
      "mine_type": "Facility",
      "primary_sic": "Aluminum Ore-Bauxite",
      "secondary_sic": "Common Clays NEC",
      "longitude": -84.14,
      "latitude": 32.196111,
      "employees_reported": 0,
      "is_active_producer": false,
      "estimated_annual_production_mt": 0,
      "recent_production_records": [],
      "company_type": "Other",
      "primary_activity": "",
      "operating_since": "",
      "no_employees": 0.0,
      "avg_employees_5yr": 0
    },
    {
      "mine_id": 900850,
      "mine_name": "Wilburn Pit No 1",
      "operator": "American Cyanamid Company",
      "state": "GA",
      "county": "",
      "status": "Abandoned",
      "mine_type": "Surface",
      "primary_sic": "Aluminum Ore-Bauxite",
      "secondary_sic": NaN,
      "longitude": NaN,
      "latitude": NaN,
      "employees_reported": 0,
      "is_active_producer": false,
      "estimated_annual_production_mt": 0,
      "recent_production_records": [],
      "company_type": "Other",
      "primary_activity": "",
      "operating_since": "",
      "no_employees": NaN,
      "avg_employees_5yr": 0
    },
    {
      "mine_id": 900921,
      "mine_name": "Dalton Alumina & Chemicals Plant",
      "operator": "Dalton Alumina & Chemicals Company",
      "state": "GA",
      "county": "",
      "status": "Abandoned",
      "mine_type": "Facility",
      "primary_sic": "Alumina",
      "secondary_sic": NaN,
      "longitude": NaN,
      "latitude": NaN,
      "employees_reported": 0,
      "is_active_producer": false,
      "estimated_annual_production_mt": 0,
      "recent_production_records": [],
      "company_type": "Other",
      "primary_activity": "",
      "operating_since": "",
      "no_employees": NaN,
      "avg_employees_5yr": 0
    },
    {
      "mine_id": 900962,
      "mine_name": "Chatsworth Plant",
      "operator": "Milwhite Inc",
      "state": "GA",
      "county": "",
      "status": "Abandoned",
      "mine_type": "Facility",
      "primary_sic": "Alumina",
      "secondary_sic": NaN,
      "longitude": NaN,
      "latitude": NaN,
      "employees_reported": 0,
      "is_active_producer": false,
      "estimated_annual_production_mt": 0,
      "recent_production_records": [],
      "company_type": "Other",
      "primary_activity": "",
      "operating_since": "",
      "no_employees": NaN,
      "avg_employees_5yr": 0
    },
    {
      "mine_id": 901216,
      "mine_name": "Wrens Plant",
      "operator": "US Ceramics LLC",
      "state": "GA",
      "county": "",
      "status": "Abandoned",
      "mine_type": "Facility",
      "primary_sic": "Clay, Ceramic, Refractory Mnls.",
      "secondary_sic": "Aluminum Ore-Bauxite",
      "longitude": -84.629722,
      "latitude": 33.801389,
      "employees_reported": 0,
      "is_active_producer": false,
      "estimated_annual_production_mt": 0,
      "recent_production_records": [],
      "company_type": "Other",
      "primary_activity": "",
      "operating_since": "",
      "no_employees": 0.0,
      "avg_employees_5yr": 0
    },
    {
      "mine_id": 1202428,
      "mine_name": "Liberty Mine",
      "operator": "Alcoa Fuels Inc.",
      "state": "IN",
      "county": "",
      "status": "NonProducing",
      "mine_type": "Surface",
      "primary_sic": "Coal (Bituminous)",
      "secondary_sic": NaN,
      "longitude": -87.3475,
      "latitude": 38.091944,
      "employees_reported": 2,
      "is_active_producer": false,
      "estimated_annual_production_mt": 0,
      "recent_production_records": [],
      "company_type": "Corporation",
      "primary_activity": "",
      "operating_since": "",
      "no_employees": 2.0,
      "avg_employees_5yr": 0
    },
    {
      "mine_id": 1600222,
      "mine_name": "Baton Rouge Alumina & Chemical",
      "operator": "Kaiser Aluminum & Chemical Corp",
      "state": "LA",
      "county": "",
      "status": "Abandoned",
      "mine_type": "Facility",
      "primary_sic": "Alumina",
      "secondary_sic": NaN,
      "longitude": NaN,
      "latitude": NaN,
      "employees_reported": 0,
      "is_active_producer": false,
      "estimated_annual_production_mt": 0,
      "recent_production_records": [],
      "company_type": "Corporation",
      "primary_activity": "",
      "operating_since": "",
      "no_employees": NaN,
      "avg_employees_5yr": 0
    },
    {
      "mine_id": 1600352,
      "mine_name": "Gramercy Operation",
      "operator": "Atalco Gramercy LLC",
      "state": "LA",
      "county": "",
      "status": "Active",
      "mine_type": "Facility",
      "primary_sic": "Alumina",
      "secondary_sic": NaN,
      "longitude": -90.659444,
      "latitude": 30.06,
      "employees_reported": 472,
      "is_active_producer": true,
      "estimated_annual_production_mt": 1038400.0,
      "recent_production_records": [],
      "company_type": "Other",
      "primary_activity": "",
      "operating_since": "",
      "no_employees": 472.0,
      "avg_employees_5yr": 0
    },
    {
      "mine_id": 1600353,
      "mine_name": "Specialty Aluminas",
      "operator": "Kaiser Aluminum & Chemical Corp",
      "state": "LA",
      "county": "",
      "status": "Abandoned",
      "mine_type": "Facility",
      "primary_sic": "Alumina",
      "secondary_sic": NaN,
      "longitude": NaN,
      "latitude": NaN,
      "employees_reported": 0,
      "is_active_producer": false,
      "estimated_annual_production_mt": 0,
      "recent_production_records": [],
      "company_type": "Corporation",
      "primary_activity": "",
      "operating_since": "",
      "no_employees": NaN,
      "avg_employees_5yr": 0
    },
    {
      "mine_id": 1600354,
      "mine_name": "LAlumina LLC",
      "operator": "LAlumina LLC",
      "state": "LA",
      "county": "",
      "status": "Abandoned",
      "mine_type": "Facility",
      "primary_sic": "Alumina",
      "secondary_sic": NaN,
      "longitude": -90.9225,
      "latitude": 30.149444,
      "employees_reported": 0,
      "is_active_producer": false,
      "estimated_annual_production_mt": 0,
      "recent_production_records": [],
      "company_type": "Other",
      "primary_activity": "",
      "operating_since": "",
      "no_employees": 0.0,
      "avg_employees_5yr": 0
    },
    {
      "mine_id": 1800351,
      "mine_name": "Kaiser Plant And Mill",
      "operator": "Refractories Div Kaiser Aluminum",
      "state": "MD",
      "county": "",
      "status": "Abandoned",
      "mine_type": "Facility",
      "primary_sic": "Fire Clay",
      "secondary_sic": NaN,
      "longitude": NaN,
      "latitude": NaN,
      "employees_reported": 0,
      "is_active_producer": false,
      "estimated_annual_production_mt": 0,
      "recent_production_records": [],
      "company_type": "Other",
      "primary_activity": "",
      "operating_since": "",
      "no_employees": NaN,
      "avg_employees_5yr": 0
    },
    {
      "mine_id": 2002985,
      "mine_name": "ROPES MILL",
      "operator": "Minerals Processing Corp",
      "state": "MI",
      "county": "",
      "status": "Abandoned",
      "mine_type": "Facility",
      "primary_sic": "Alumina",
      "secondary_sic": NaN,
      "longitude": NaN,
      "latitude": NaN,
      "employees_reported": 0,
      "is_active_producer": false,
      "estimated_annual_production_mt": 0,
      "recent_production_records": [],
      "company_type": "Corporation",
      "primary_activity": "",
      "operating_since": "",
      "no_employees": NaN,
      "avg_employees_5yr": 0
    },
    {
      "mine_id": 2301045,
      "mine_name": "Jones",
      "operator": "Kaiser Aluminum & Chemical Corp",
      "state": "MO",
      "county": "",
      "status": "Abandoned",
      "mine_type": "Surface",
      "primary_sic": "Fire Clay",
      "secondary_sic": NaN,
      "longitude": NaN,
      "latitude": NaN,
      "employees_reported": 0,
      "is_active_producer": false,
      "estimated_annual_production_mt": 0,
      "recent_production_records": [],
      "company_type": "Corporation",
      "primary_activity": "",
      "operating_since": "",
      "no_employees": NaN,
      "avg_employees_5yr": 0
    },
    {
      "mine_id": 2301046,
      "mine_name": "Snook",
      "operator": "Kaiser Aluminum & Chemical Corp",
      "state": "MO",
      "county": "",
      "status": "Abandoned",
      "mine_type": "Surface",
      "primary_sic": "Common Clays NEC",
      "secondary_sic": NaN,
      "longitude": NaN,
      "latitude": NaN,
      "employees_reported": 0,
      "is_active_producer": false,
      "estimated_annual_production_mt": 0,
      "recent_production_records": [],
      "company_type": "Corporation",
      "primary_activity": "",
      "operating_since": "",
      "no_employees": NaN,
      "avg_employees_5yr": 0
    },
    {
      "mine_id": 2301047,
      "mine_name": "Kaiser Mine No 1",
      "operator": "Kaiser Aluminum & Chemical Corp",
      "state": "MO",
      "county": "",
      "status": "Abandoned",
      "mine_type": "Surface",
      "primary_sic": "Common Shale",
      "secondary_sic": NaN,
      "longitude": NaN,
      "latitude": NaN,
      "employees_reported": 0,
      "is_active_producer": false,
      "estimated_annual_production_mt": 0,
      "recent_production_records": [],
      "company_type": "Corporation",
      "primary_activity": "",
      "operating_since": "",
      "no_employees": NaN,
      "avg_employees_5yr": 0
    },
    {
      "mine_id": 2301449,
      "mine_name": "Erdel",
      "operator": "Kaiser Aluminum & Chemical Corp",
      "state": "MO",
      "county": "",
      "status": "Abandoned",
      "mine_type": "Surface",
      "primary_sic": "Common Clays NEC",
      "secondary_sic": NaN,
      "longitude": NaN,
      "latitude": NaN,
      "employees_reported": 0,
      "is_active_producer": false,
      "estimated_annual_production_mt": 0,
      "recent_production_records": [],
      "company_type": "Corporation",
      "primary_activity": "",
      "operating_since": "",
      "no_employees": NaN,
      "avg_employees_5yr": 0
    },
    {
      "mine_id": 2301453,
      "mine_name": "Drake Stockpile",
      "operator": "Kaiser Aluminum & Chemical Corp",
      "state": "MO",
      "county": "",
      "status": "Abandoned",
      "mine_type": "Surface",
      "primary_sic": "Common Clays NEC",
      "secondary_sic": NaN,
      "longitude": NaN,
      "latitude": NaN,
      "employees_reported": 0,
      "is_active_producer": false,
      "estimated_annual_production_mt": 0,
      "recent_production_records": [],
      "company_type": "Corporation",
      "primary_activity": "",
      "operating_since": "",
      "no_employees": NaN,
      "avg_employees_5yr": 0
    },
    {
      "mine_id": 2301830,
      "mine_name": "Bauxite Crushing Plant",
      "operator": "Sonneborn Refrac & Chemicals Inc",
      "state": "MO",
      "county": "",
      "status": "Abandoned",
      "mine_type": "Facility",
      "primary_sic": "Alumina",
      "secondary_sic": NaN,
      "longitude": NaN,
      "latitude": NaN,
      "employees_reported": 0,
      "is_active_producer": false,
      "estimated_annual_production_mt": 0,
      "recent_production_records": [],
      "company_type": "Other",
      "primary_activity": "",
      "operating_since": "",
      "no_employees": NaN,
      "avg_employees_5yr": 0
    },
    {
      "mine_id": 3100233,
      "mine_name": "Hillsborough Mine ",
      "operator": "Resco Products Inc",
      "state": "NC",
      "county": "",
      "status": "Active",
      "mine_type": "Surface",
      "primary_sic": "Alumina",
      "secondary_sic": NaN,
      "longitude": -79.104722,
      "latitude": 36.070193,
      "employees_reported": 18,
      "is_active_producer": true,
      "estimated_annual_production_mt": 39600.0,
      "recent_production_records": [],
      "company_type": "Corporation",
      "primary_activity": "",
      "operating_since": "",
      "no_employees": 18.0,
      "avg_employees_5yr": 0
    },
    {
      "mine_id": 3600645,
      "mine_name": "Potato Ridge Clay Mine",
      "operator": "Kaiser Aluminum & Chemical Corp",
      "state": "PA",
      "county": "",
      "status": "Abandoned",
      "mine_type": "Surface",
      "primary_sic": "Fire Clay",
      "secondary_sic": NaN,
      "longitude": NaN,
      "latitude": NaN,
      "employees_reported": 0,
      "is_active_producer": false,
      "estimated_annual_production_mt": 0,
      "recent_production_records": [],
      "company_type": "Corporation",
      "primary_activity": "",
      "operating_since": "",
      "no_employees": NaN,
      "avg_employees_5yr": 0
    },
    {
      "mine_id": 3605333,
      "mine_name": "Sproul Works",
      "operator": "General Refractories Company",
      "state": "PA",
      "county": "",
      "status": "Abandoned",
      "mine_type": "Facility",
      "primary_sic": "Alumina",
      "secondary_sic": NaN,
      "longitude": NaN,
      "latitude": NaN,
      "employees_reported": 0,
      "is_active_producer": false,
      "estimated_annual_production_mt": 0,
      "recent_production_records": [],
      "company_type": "Other",
      "primary_activity": "",
      "operating_since": "",
      "no_employees": NaN,
      "avg_employees_5yr": 0
    },
    {
      "mine_id": 3610222,
      "mine_name": "Leetsdale PA",
      "operator": "Almatis Inc",
      "state": "PA",
      "county": "",
      "status": "Active",
      "mine_type": "Facility",
      "primary_sic": "Alumina",
      "secondary_sic": NaN,
      "longitude": -80.218611,
      "latitude": 40.565833,
      "employees_reported": 98,
      "is_active_producer": true,
      "estimated_annual_production_mt": 215600.0,
      "recent_production_records": [],
      "company_type": "Corporation",
      "primary_activity": "",
      "operating_since": "",
      "no_employees": 98.0,
      "avg_employees_5yr": 0
    },
    {
      "mine_id": 4100320,
      "mine_name": "Bayer Alumina Plant",
      "operator": "Alcoa World Alumina LLC",
      "state": "TX",
      "county": "",
      "status": "Abandoned",
      "mine_type": "Facility",
      "primary_sic": "Alumina",
      "secondary_sic": NaN,
      "longitude": -96.560278,
      "latitude": 28.679722,
      "employees_reported": 0,
      "is_active_producer": false,
      "estimated_annual_production_mt": 0,
      "recent_production_records": [],
      "company_type": "Other",
      "primary_activity": "",
      "operating_since": "",
      "no_employees": NaN,
      "avg_employees_5yr": 0
    },
    {
      "mine_id": 4100356,
      "mine_name": "Sandow Mine",
      "operator": "Alcoa Inc",
      "state": "TX",
      "county": "",
      "status": "Abandoned",
      "mine_type": "Surface",
      "primary_sic": "Coal (Lignite)",
      "secondary_sic": NaN,
      "longitude": -97.083333,
      "latitude": 30.541666,
      "employees_reported": 0,
      "is_active_producer": false,
      "estimated_annual_production_mt": 0,
      "recent_production_records": [],
      "company_type": "Corporation",
      "primary_activity": "",
      "operating_since": "",
      "no_employees": 0.0,
      "avg_employees_5yr": 0
    },
    {
      "mine_id": 4100906,
      "mine_name": "Sherwin Alumina, L.P.",
      "operator": "Sherwin Alumina Company, LLC",
      "state": "TX",
      "county": "",
      "status": "Abandoned",
      "mine_type": "Facility",
      "primary_sic": "Alumina",
      "secondary_sic": NaN,
      "longitude": -97.29,
      "latitude": 27.922222,
      "employees_reported": 0,
      "is_active_producer": false,
      "estimated_annual_production_mt": 0,
      "recent_production_records": [],
      "company_type": "Other",
      "primary_activity": "",
      "operating_since": "",
      "no_employees": NaN,
      "avg_employees_5yr": 0
    },
    {
      "mine_id": 4102721,
      "mine_name": "Houston Plant (Manchester)",
      "operator": "Stauffer Chemical Company",
      "state": "TX",
      "county": "",
      "status": "Abandoned",
      "mine_type": "Facility",
      "primary_sic": "Aluminum Ore-Bauxite",
      "secondary_sic": NaN,
      "longitude": NaN,
      "latitude": NaN,
      "employees_reported": 0,
      "is_active_producer": false,
      "estimated_annual_production_mt": 0,
      "recent_production_records": [],
      "company_type": "Other",
      "primary_activity": "",
      "operating_since": "",
      "no_employees": NaN,
      "avg_employees_5yr": 0
    },
    {
      "mine_id": 4200154,
      "mine_name": "Bonneville Plant",
      "operator": "Kaiser Aluminum & Chemical Corp",
      "state": "UT",
      "county": "",
      "status": "Abandoned",
      "mine_type": "Surface",
      "primary_sic": "Potash",
      "secondary_sic": NaN,
      "longitude": NaN,
      "latitude": NaN,
      "employees_reported": 0,
      "is_active_producer": false,
      "estimated_annual_production_mt": 0,
      "recent_production_records": [],
      "company_type": "Corporation",
      "primary_activity": "",
      "operating_since": "",
      "no_employees": NaN,
      "avg_employees_5yr": 0
    },
    {
      "mine_id": 4608706,
      "mine_name": "Mine No 1",
      "operator": "Walcoal, Inc",
      "state": "WV",
      "county": "",
      "status": "Abandoned and Sealed",
      "mine_type": "Underground",
      "primary_sic": "Coal (Bituminous)",
      "secondary_sic": NaN,
      "longitude": -81.498611,
      "latitude": 37.262777,
      "employees_reported": 0,
      "is_active_producer": false,
      "estimated_annual_production_mt": 0,
      "recent_production_records": [],
      "company_type": "Corporation",
      "primary_activity": "",
      "operating_since": "",
      "no_employees": 0.0,
      "avg_employees_5yr": 0
    },
    {
      "mine_id": 4608970,
      "mine_name": "Mine No. 2",
      "operator": "Walcoal, Inc.",
      "state": "WV",
      "county": "",
      "status": "Abandoned and Sealed",
      "mine_type": "Underground",
      "primary_sic": "Coal (Bituminous)",
      "secondary_sic": NaN,
      "longitude": -81.479166,
      "latitude": 37.2625,
      "employees_reported": 0,
      "is_active_producer": false,
      "estimated_annual_production_mt": 0,
      "recent_production_records": [],
      "company_type": "Corporation",
      "primary_activity": "",
      "operating_since": "",
      "no_employees": 0.0,
      "avg_employees_5yr": 0
    },
    {
      "mine_id": 4609571,
      "mine_name": "FX Minerals Processing, Inc.",
      "operator": "FX Minerals Processing, Inc.",
      "state": "WV",
      "county": "",
      "status": "Active",
      "mine_type": "Facility",
      "primary_sic": "Alumina",
      "secondary_sic": NaN,
      "longitude": -80.619722,
      "latitude": 40.615,
      "employees_reported": 25,
      "is_active_producer": true,
      "estimated_annual_production_mt": 55000.0,
      "recent_production_records": [],
      "company_type": "Corporation",
      "primary_activity": "",
      "operating_since": "",
      "no_employees": 25.0,
      "avg_employees_5yr": 0
    },
    {
      "mine_id": 5500005,
      "mine_name": "St. Croix Alumina, LLC",
      "operator": "St. Croix Alumina, LLC",
      "state": "VI",
      "county": "",
      "status": "Abandoned",
      "mine_type": "Surface",
      "primary_sic": "Alumina",
      "secondary_sic": NaN,
      "longitude": -64.783627,
      "latitude": 17.725296,
      "employees_reported": 0,
      "is_active_producer": false,
      "estimated_annual_production_mt": 0,
      "recent_production_records": [],
      "company_type": "Other",
      "primary_activity": "",
      "operating_since": "",
      "no_employees": 0.0,
      "avg_employees_5yr": 0
    }
  ],
  "active_production_summary": [
    {
      "rank": 1,
      "mine_id": 1600352,
      "mine_name": "Gramercy Operation",
      "state": "LA",
      "status": "Active",
      "mine_type": "Facility",
      "operator": "Atalco Gramercy LLC",
      "primary_sic": "Alumina",
      "employees": 472.0,
      "estimated_annual_production_mt": 1038400.0,
      "production_factor_mt_per_employee": 2200,
      "confidence_level": "high",
      "longitude": -90.659444,
      "latitude": 30.06,
      "metal": "aluminum",
      "verification_method": "exact_sic",
      "verification_notes": "Clear SIC codes for alumina and bauxite",
      "expected_us_production": "significant"
    },
    {
      "rank": 2,
      "mine_id": 300257,
      "mine_name": "Arkansas Operations Mill",
      "state": "AR",
      "status": "Active",
      "mine_type": "Facility",
      "operator": "Almatis Inc",
      "primary_sic": "Alumina",
      "employees": 140.0,
      "estimated_annual_production_mt": 308000.0,
      "production_factor_mt_per_employee": 2200,
      "confidence_level": "high",
      "longitude": -92.535278,
      "latitude": 34.582778,
      "metal": "aluminum",
      "verification_method": "exact_sic",
      "verification_notes": "Clear SIC codes for alumina and bauxite",
      "expected_us_production": "significant"
    },
    {
      "rank": 3,
      "mine_id": 3610222,
      "mine_name": "Leetsdale PA",
      "state": "PA",
      "status": "Active",
      "mine_type": "Facility",
      "operator": "Almatis Inc",
      "primary_sic": "Alumina",
      "employees": 98.0,
      "estimated_annual_production_mt": 215600.0,
      "production_factor_mt_per_employee": 2200,
      "confidence_level": "high",
      "longitude": -80.218611,
      "latitude": 40.565833,
      "metal": "aluminum",
      "verification_method": "exact_sic",
      "verification_notes": "Clear SIC codes for alumina and bauxite",
      "expected_us_production": "significant"
    },
    {
      "rank": 4,
      "mine_id": 302023,
      "mine_name": "Huber Specialty Hydrates, LLC ",
      "state": "AR",
      "status": "Active",
      "mine_type": "Facility",
      "operator": "Huber Specialty Hydrates, LLC ",
      "primary_sic": "Aluminum Ore-Bauxite",
      "employees": 80.0,
      "estimated_annual_production_mt": 176000.0,
      "production_factor_mt_per_employee": 2200,
      "confidence_level": "high",
      "longitude": -92.535278,
      "latitude": 34.582778,
      "metal": "aluminum",
      "verification_method": "exact_sic",
      "verification_notes": "Clear SIC codes for alumina and bauxite",
      "expected_us_production": "significant"
    },
    {
      "rank": 5,
      "mine_id": 301979,
      "mine_name": "Section 27",
      "state": "AR",
      "status": "Active",
      "mine_type": "Surface",
      "operator": "SEMCOA",
      "primary_sic": "Aluminum Ore-Bauxite",
      "employees": 27.0,
      "estimated_annual_production_mt": 59400.0,
      "production_factor_mt_per_employee": 2200,
      "confidence_level": "high",
      "longitude": -92.513611,
      "latitude": 34.535,
      "metal": "aluminum",
      "verification_method": "exact_sic",
      "verification_notes": "Clear SIC codes for alumina and bauxite",
      "expected_us_production": "significant"
    },
    {
      "rank": 6,
      "mine_id": 4609571,
      "mine_name": "FX Minerals Processing, Inc.",
      "state": "WV",
      "status": "Active",
      "mine_type": "Facility",
      "operator": "FX Minerals Processing, Inc.",
      "primary_sic": "Alumina",
      "employees": 25.0,
      "estimated_annual_production_mt": 55000.0,
      "production_factor_mt_per_employee": 2200,
      "confidence_level": "high",
      "longitude": -80.619722,
      "latitude": 40.615,
      "metal": "aluminum",
      "verification_method": "exact_sic",
      "verification_notes": "Clear SIC codes for alumina and bauxite",
      "expected_us_production": "significant"
    },
    {
      "rank": 7,
      "mine_id": 3100233,
      "mine_name": "Hillsborough Mine ",
      "state": "NC",
      "status": "Active",
      "mine_type": "Surface",
      "operator": "Resco Products Inc",
      "primary_sic": "Alumina",
      "employees": 18.0,
      "estimated_annual_production_mt": 39600.0,
      "production_factor_mt_per_employee": 2200,
      "confidence_level": "high",
      "longitude": -79.104722,
      "latitude": 36.070193,
      "metal": "aluminum",
      "verification_method": "exact_sic",
      "verification_notes": "Clear SIC codes for alumina and bauxite",
      "expected_us_production": "significant"
    },
    {
      "rank": 8,
      "mine_id": 300261,
      "mine_name": "U.S. Vanadium - Benton, LLC",
      "state": "AR",
      "status": "Active",
      "mine_type": "Surface",
      "operator": "US Vanadium - Benton, LLC",
      "primary_sic": "Aluminum Ore-Bauxite",
      "employees": 5.0,
      "estimated_annual_production_mt": 11000.0,
      "production_factor_mt_per_employee": 2200,
      "confidence_level": "high",
      "longitude": -92.516389,
      "latitude": 34.583889,
      "metal": "aluminum",
      "verification_method": "exact_sic",
      "verification_notes": "Clear SIC codes for alumina and bauxite",
      "expected_us_production": "significant"
    }
  ],
  "analysis_notes": "Clear SIC codes for alumina and bauxite",
  "data_sources": "MSHA Mine Safety and Health Administration data"
}